pubcrank/__init__.py
pubcrank/admin.py
pubcrank/apps.py
pubcrank/bin.py
pubcrank/crank.py
pubcrank/lib/__init__.py
pubcrank/lib/frontmatter.py
pubcrank/migrations/0001_initial.py
pubcrank/migrations/__init__.py
pubcrank/models.py
pubcrank/pagination.py
pubcrank/serialize.py
pubcrank/settings.py
pubcrank/templatetags/__init__.py
pubcrank/templatetags/pubcrank.py
pubcrank/tests.py
pubcrank/views.py
pubcrank_django_app-0.5.0.dist-info/METADATA
pubcrank_django_app-0.5.0.dist-info/WHEEL
pubcrank_django_app-0.5.0.dist-info/entry_points.txt
pubcrank_django_app-0.5.0.dist-info/RECORD
