Metadata-Version: 2.1
Name: pubcrank-django-app
Version: 0.5.0
Summary: PubCrank CMS Django App
Author-Email: Paul Bailey <paul@neutron.studio>
License: BSD 3-Clause
Project-URL: homepage, https://www.pubcrank.md/
Requires-Python: >=3.13
Requires-Dist: piou>=0.16.2
Requires-Dist: hjson>=3.1.0
Requires-Dist: python-frontmatter>=1.1.0
Requires-Dist: markdown2[all]>=2.5.3
Requires-Dist: pendulum>=3.1.0
